lasy/__init__.py
lasy/laser.py
lasy/optical_elements/__init__.py
lasy/optical_elements/axicon.py
lasy/optical_elements/axiparabola.py
lasy/optical_elements/chromatic_lens.py
lasy/optical_elements/intensity_mask.py
lasy/optical_elements/optical_element.py
lasy/optical_elements/parabolic_mirror.py
lasy/optical_elements/polynomial_spectral_phase.py
lasy/optical_elements/spectral_filter.py
lasy/optical_elements/spectral_phase.py
lasy/optical_elements/zernike_aberrations.py
lasy/profiles/__init__.py
lasy/profiles/combined_profile.py
lasy/profiles/from_array_profile.py
lasy/profiles/from_insight_file.py
lasy/profiles/from_openpmd_profile.py
lasy/profiles/gaussian_profile.py
lasy/profiles/profile.py
lasy/profiles/speckle_profile.py
lasy/profiles/longitudinal/__init__.py
lasy/profiles/longitudinal/continuous_wave_profile.py
lasy/profiles/longitudinal/cosine_profile.py
lasy/profiles/longitudinal/gaussian_profile.py
lasy/profiles/longitudinal/longitudinal_profile.py
lasy/profiles/longitudinal/longitudinal_profile_from_data.py
lasy/profiles/longitudinal/super_gaussian_profile.py
lasy/profiles/transverse/__init__.py
lasy/profiles/transverse/flattened_gaussian_profile.py
lasy/profiles/transverse/gaussian_profile.py
lasy/profiles/transverse/hermite_gaussian_profile.py
lasy/profiles/transverse/jinc_profile.py
lasy/profiles/transverse/laguerre_gaussian_profile.py
lasy/profiles/transverse/plane_wave_profile.py
lasy/profiles/transverse/super_gaussian_profile.py
lasy/profiles/transverse/transverse_profile.py
lasy/profiles/transverse/transverse_profile_from_data.py
lasy/propagators/__init__.py
lasy/propagators/abcd.py
lasy/propagators/angular_spectrum_propagator.py
lasy/propagators/axiprop_propagators.py
lasy/propagators/collins_sfft_propagator.py
lasy/propagators/fresnel_chirpztransform_propagator.py
lasy/propagators/fresnel_sfft_propagator.py
lasy/propagators/nonlinear_phase_shift.py
lasy/propagators/propagator.py
lasy/propagators/single_fft_propagator.py
lasy/utils/__init__.py
lasy-0.7.0.dist-info/METADATA
lasy-0.7.0.dist-info/WHEEL
lasy-0.7.0.dist-info/legal.txt
lasy-0.7.0.dist-info/license.txt
lasy-0.7.0.dist-info/top_level.txt
lasy-0.7.0.dist-info/RECORD
