Metadata-Version: 2.1
Name: lasy
Version: 0.7.0
Summary: LAser pulse manipulation made eaSY
Home-page: https://github.com/LASY-org/lasy
Author: Rob Shalloo, Maxence Thevenet, Remi Lehe, Axel Huebl, Igor Adriyash, Soeren Jalas, Angel Ferran Pousa, Luca Fedeli
Maintainer: Maxence Thevenet, Remi Lehe, Axel Huebl
Maintainer-email: maxence.thevenet@desy.de, rlehe@lbl.gov, axelhuebl@lbl.gov
License: BSD-3-Clause-LBNL
Project-URL: Documentation, https://lasydoc.readthedocs.io
Project-URL: Source, https://github.com/LASY-org/lasy
Project-URL: Tracker, https://github.com/LASY-org/lasy/issues
Classifier: Development Status :: 3 - Alpha
Classifier: Natural Language :: English
Classifier: Environment :: Console
Classifier: Intended Audience :: Science/Research
Classifier: Operating System :: OS Independent
Classifier: Topic :: Scientific/Engineering
Classifier: Programming Language :: Python :: 3
Classifier: License :: OSI Approved :: BSD License
Requires-Python: >=3.7
License-File: license.txt
License-File: legal.txt
Requires-Dist: axiprop >=0.5.5
Requires-Dist: matplotlib
Requires-Dist: numpy
Requires-Dist: openpmd-api >=0.16.1
Requires-Dist: pyyaml
Requires-Dist: scipy
Provides-Extra: tests
Requires-Dist: pytest ; extra == 'tests'
